pytyran/__init__.py
pytyran/client.py
pytyran/logger.py
pytyran/reader.py
pytyran-0.1.5.dist-info/LICENSE.txt
pytyran-0.1.5.dist-info/METADATA
pytyran-0.1.5.dist-info/WHEEL
pytyran-0.1.5.dist-info/top_level.txt
pytyran-0.1.5.dist-info/RECORD
